setup.cfg
setup.py
targetinteractionfinder/__init__.py
targetinteractionfinder/parse_bridgedb_datasources.py
targetinteractionfinder/regexes.py
targetinteractionfinder/target_interaction_finder.py
targetinteractionfinder.egg-info/PKG-INFO
targetinteractionfinder.egg-info/SOURCES.txt
targetinteractionfinder.egg-info/dependency_links.txt
targetinteractionfinder.egg-info/requires.txt
targetinteractionfinder.egg-info/top_level.txt