Metadata-Version: 1.1
Name: targetinteractionfinder
Version: 0.0.1
Summary: Map exRNA to proteins
Home-page: https://github.com/ariutta/target-interaction-finder
Author: Anders Riutta
Author-email: UNKNOWN
License: Apache-2.0
Keywords: Network Biology,Biological Pathways
Platform: UNKNOWN
Classifier: Development Status :: 3 - Alpha
Classifier: Intended Audience :: Science/Research
Classifier: Topic :: Scientific/Engineering :: Bio-Informatics
Classifier: License :: OSI Approved :: Apache Software License
Classifier: Programming Language :: Python :: 2
